README.rst
setup.py
reportlogging/__init__.py
reportlogging.egg-info/PKG-INFO
reportlogging.egg-info/SOURCES.txt
reportlogging.egg-info/dependency_links.txt
reportlogging.egg-info/entry_points.txt
reportlogging.egg-info/not-zip-safe
reportlogging.egg-info/pbr.json
reportlogging.egg-info/requires.txt
reportlogging.egg-info/top_level.txt