Metadata-Version: 1.1
Name: reportlogging
Version: 0.0
Summary: logging interface for report messages
Home-page: https://github.com/podhmo/reportlogging
Author: podhmo
Author-email: UNKNOWN
License: UNKNOWN
Keywords: logging
Platform: UNKNOWN
Classifier: Programming Language :: Python
Classifier: Programming Language :: Python :: Implementation :: CPython
